MD2K_Cerebral_Cortex-3.0.0.dist-info/DESCRIPTION.rst
MD2K_Cerebral_Cortex-3.0.0.dist-info/METADATA
MD2K_Cerebral_Cortex-3.0.0.dist-info/RECORD
MD2K_Cerebral_Cortex-3.0.0.dist-info/WHEEL
MD2K_Cerebral_Cortex-3.0.0.dist-info/entry_points.txt
MD2K_Cerebral_Cortex-3.0.0.dist-info/metadata.json
MD2K_Cerebral_Cortex-3.0.0.dist-info/top_level.txt
cerebralcortex/__init__.py
cerebralcortex/cerebralcortex.py
cerebralcortex/core/__init__.py
cerebralcortex/core/config_manager/__init__.py
cerebralcortex/core/config_manager/config.py
cerebralcortex/core/config_manager/config_handler.py
cerebralcortex/core/data_manager/__init__.py
cerebralcortex/core/data_manager/object/__init__.py
cerebralcortex/core/data_manager/object/data.py
cerebralcortex/core/data_manager/object/storage_filesystem.py
cerebralcortex/core/data_manager/object/storage_minio.py
cerebralcortex/core/data_manager/raw/__init__.py
cerebralcortex/core/data_manager/raw/data.py
cerebralcortex/core/data_manager/raw/storage_blueprint.py
cerebralcortex/core/data_manager/raw/storage_filesystem.py
cerebralcortex/core/data_manager/raw/storage_hdfs.py
cerebralcortex/core/data_manager/raw/stream_handler.py
cerebralcortex/core/data_manager/sql/__init__.py
cerebralcortex/core/data_manager/sql/cache_handler.py
cerebralcortex/core/data_manager/sql/data.py
cerebralcortex/core/data_manager/sql/kafka_offsets_handler.py
cerebralcortex/core/data_manager/sql/stream_handler.py
cerebralcortex/core/data_manager/sql/users_handler.py
cerebralcortex/core/data_manager/time_series/__init__.py
cerebralcortex/core/data_manager/time_series/data.py
cerebralcortex/core/data_manager/time_series/influxdb_handler.py
cerebralcortex/core/datatypes/__init__.py
cerebralcortex/core/datatypes/datastream.py
cerebralcortex/core/log_manager/__init__.py
cerebralcortex/core/log_manager/log_handler.py
cerebralcortex/core/log_manager/logging.py
cerebralcortex/core/messaging_manager/__init__.py
cerebralcortex/core/messaging_manager/kafka_handler.py
cerebralcortex/core/messaging_manager/messaging_queue.py
cerebralcortex/core/metadata_manager/__init__.py
cerebralcortex/core/metadata_manager/stream/__init__.py
cerebralcortex/core/metadata_manager/stream/data_descriptor.py
cerebralcortex/core/metadata_manager/stream/metadata.py
