Metadata-Version: 2.0
Name: MD2K-Cerebral-Cortex
Version: 3.0.0
Summary: Backend data analytics platform for MD2K software
Home-page: https://github.com/MD2Korg/CerebralCortex-Kernel/archive/3.0.0.zip
Author: MD2K.org
Author-email: dev@md2k.org
License: BSD2
Keywords: mHealth machine-learning data-analysis
Platform: UNKNOWN
Classifier: Development Status :: 5 - Production/Stable
Classifier: Intended Audience :: Healthcare Industry
Classifier: Intended Audience :: Science/Research
Classifier: License :: OSI Approved :: BSD License
Classifier: Natural Language :: English
Classifier: Programming Language :: Python :: 3
Classifier: Topic :: Scientific/Engineering :: Information Analysis
Classifier: Topic :: System :: Distributed Computing
Requires-Dist: PyJWT (==1.7.1)
Requires-Dist: PyYAML (==4.2b1)
Requires-Dist: hdfs3 (==0.3.0)
Requires-Dist: influxdb (==5.2.1)
Requires-Dist: kafka (==1.3.5)
Requires-Dist: minio (==2.2.4)
Requires-Dist: mysql-connector-python-rf (==2.2.2)
Requires-Dist: numpy (==1.14.5)
Requires-Dist: pennprov (==2.2.0.dev3)
Requires-Dist: pyarrow (==0.11.1)
Requires-Dist: pympler (==0.5)
Requires-Dist: pyspark (==2.4.0)
Requires-Dist: pytz (==2017.2)
Requires-Dist: wheel (==0.29.0)
